boardofdirectors/__init__.py
boardofdirectors/core.py
boardofdirectors-0.1.7.dist-info/METADATA
boardofdirectors-0.1.7.dist-info/WHEEL
boardofdirectors-0.1.7.dist-info/top_level.txt
boardofdirectors-0.1.7.dist-info/RECORD
