Metadata-Version: 2.1
Name: boardofdirectors
Version: 0.1.7
Summary: cmiuc
Author: Pseudonym
Author-email: audiodramaa@gmail.com
Classifier: Programming Language :: Python :: 3
Classifier: License :: OSI Approved :: MIT License
Classifier: Operating System :: OS Independent
Requires-Python: >=3.6
